[
    {
        "cart": [],
        "email": "buyer1@gmail.com",
        "name": "abimanyu",
        "orders": [
            "order001",
            "XPe9Tp9Z"
        ],
        "password": "abimanyu",
        "quantity": [],
        "state": "tamilnadu",
        "username": "buyer001"
    },
    {
        "cart": [],
        "email": "buyer2@gmail.com",
        "name": "yuvraj",
        "orders": [
            "order002"
        ],
        "password": "abimanyu",
        "quantity": [],
        "state": "tamilnadu",
        "username": "buyer002"
    }
]